{
  "tool_name": "execute",
  "agent_name": "web_agent",
  "session_id": "41888d3802ef",
  "timestamp": "2026-04-29T06:20:38.329262+00:00",
  "input": {
    "command": "tvly search \"Colombo weather site:weather.com\" --json",
    "timeout_seconds": 120
  },
  "output_chars": 2424,
  "output": "exit_code=0\n{\n  \"query\": \"Colombo weather\",\n  \"follow_up_questions\": null,\n  \"answer\": null,\n  \"images\": [],\n  \"results\": [\n    {\n      \"url\": \"https://weather.com/weather/hourbyhour/l/0a718df3f313b9b503468fc5d83fabf32db2a98f7376bbab34bf69361ef16336\",\n      \"title\": \"Hourly Weather Forecast for Colombo, Sri Lanka\",\n      \"content\": \"Hourly Weather Colombo, Sri Lanka \u00b7 as of 5:00 PM PDT \u00b7 1 pm. Partly Cloudy. 104\u00b089\u00b0 \u00b7 2 pm. Mostly Sunny. 105\u00b089\u00b0 \u00b7 3 pm. Partly Cloudy. 104\u00b089\u00b0 \u00b7 4 pm. Partly\",\n      \"score\": 0.9999329,\n      \"raw_content\": null\n    },\n    {\n      \"url\": \"https://weather.com/weather/monthly/l/Colombo+Sri+Lanka?placeId=f98de3c9fffcbc8b4a2dcccb6d31ab867040462b7a8fedb2a877cb13f4ddf0bf\",\n      \"title\": \"Monthly Weather Forecast for Colombo, Sri Lanka\",\n      \"content\": \"Scattered clouds with the possibility of an isolated thunderstorm developing during the afternoon. High 89F. Winds S at 10 to 15 mph. Chance of rain 30%.\",\n      \"score\": 0.9998697,\n      \"raw_content\": null\n    },\n    {\n      \"url\": \"https://weather.com/weather/hourbyhour/l/33784c6db40d624986cda0da6f9da4cb4b2c0d1341a94c600ea5fd59dd68449c\",\n      \"title\": \"Hourly Weather Forecast for Nawala, Colombo, Sri Lanka\",\n      \"content\": \"Mostly Cloudy. 93\u00b082\u00b0. 11 pm. 34%. Few Showers. 91\u00b081\u00b0. Wednesday, April 29. 12 am. Mostly Cloudy. 91\u00b081\u00b0. Advertisement. 1 am. Mostly Cloudy. 90\u00b080\u00b0. 2 am.\",\n      \"score\": 0.9998591,\n      \"raw_content\": null\n    },\n    {\n      \"url\": \"https://weather.com/weather/hourbyhour/l/2efa1f88b1403e34f1aac75e77ae720607ad52fcfc6fe84c7a4d0a8027a11c68\",\n      \"title\": \"Hourly Weather Forecast for TownHall, Colombo, Sri Lanka\",\n      \"content\": \"90\u00b081\u00b0. 10 pm. Mostly Cloudy. 90\u00b081\u00b0. 11 pm. Mostly Cloudy. 90\u00b081\u00b0. Wednesday, April 29. 12 am. Mostly Cloudy. 91\u00b082\u00b0. 1 am. Mostly Cloudy. 90\u00b081\u00b0. 2 am. Mostly\",\n      \"score\": 0.99984276,\n      \"raw_content\": null\n    },\n    {\n      \"url\": \"https://weather.com/weather/hourbyhour/l/Nawala+Colombo+Sri+Lanka?canonicalCityId=da932375b8441208d3de2165d2d36166\",\n      \"title\": \"Hourly Weather Forecast for Nawala, Colombo, Sri Lanka\",\n      \"content\": \"10 pm. Mostly Cloudy. 89\u00b080\u00b0. 11 pm. Mostly Cloudy. 88\u00b079\u00b0. Wednesday, April 29. 12 am. Mostly Cloudy. 88\u00b079\u00b0. 1 am. Mostly Cloudy. 88\u00b079\u00b0. 2 am. Mostly Cloudy.\",\n      \"score\": 0.9997749,\n      \"raw_content\": null\n    }\n  ],\n  \"response_time\": 1.14,\n  \"request_id\": \"5f90ea83-7160-4f41-be69-9923770a7e26\"\n}\n",
  "call_id": "3"
}